gpti/__init__.py
gpti/util.py
gpti-2.1.dist-info/LICENSE
gpti-2.1.dist-info/METADATA
gpti-2.1.dist-info/WHEEL
gpti-2.1.dist-info/top_level.txt
gpti-2.1.dist-info/RECORD
