Metadata-Version: 2.1
Name: gpti
Version: 2.1
Summary: This package simplifies your interaction with various GPT models, removing the need for tokens or other methods to access GPT
Home-page: https://github.com/yandricr/gpti-py/
Author: yandricr
Author-email: yandribret@gmail.com
License: MIT
Project-URL: Documentation, https://nexra.aryahcr.cc/
Project-URL: Source, https://github.com/yandricr/gpti-py/
Keywords: gpt gpt-3 gpt-3.5 gpt-4 gpti gpt-free ai blackbox prodia bing chat stream dalle generate-image llama-3.1 gpt-4o
License-File: LICENSE
Requires-Dist: requests
